neurojack/__init__.py
neurojack/agent/__init__.py
neurojack/agent/double_dqn_agent.py
neurojack/agent/dqn_agent.py
neurojack/env/__init__.py
neurojack/env/card.py
neurojack/env/deck.py
neurojack/env/env.py
neurojack/env/playerhand.py
neurojack/env/values.py
neurojack/memory/replay_buffer.py
neurojack/model/q_model.py
neurojack-0.1.1.dist-info/LICENSE
neurojack-0.1.1.dist-info/METADATA
neurojack-0.1.1.dist-info/WHEEL
neurojack-0.1.1.dist-info/RECORD
