Metadata-Version: 2.3
Name: neurojack
Version: 0.1.1
Summary: 
Author: dafaqboomduck
Requires-Python: >=3.10, <3.11
Classifier: Programming Language :: Python :: 3
Classifier: Programming Language :: Python :: 3.10
Requires-Dist: matplotlib (==3.10.5)
Requires-Dist: matplotlib-inline (>=0.1.7,<0.2.0)
Requires-Dist: numpy (==2.0.1)
Requires-Dist: tensorflow (==2.18.0)
Requires-Dist: tensorflow-io-gcs-filesystem (>0.28.0,<0.30.0)
Requires-Dist: tqdm (==4.67.1)
